fastuiwidgets/__init__.py
fastuiwidgets/_rc/__init__.py
fastuiwidgets/_rc/resource.py
fastuiwidgets/common/__init__.py
fastuiwidgets/common/animation.py
fastuiwidgets/common/auto_wrap.py
fastuiwidgets/common/color.py
fastuiwidgets/common/config.py
fastuiwidgets/common/exception_handler.py
fastuiwidgets/common/font.py
fastuiwidgets/common/icon.py
fastuiwidgets/common/image_utils.py
fastuiwidgets/common/overload.py
fastuiwidgets/common/router.py
fastuiwidgets/common/screen.py
fastuiwidgets/common/smooth_scroll.py
fastuiwidgets/common/style_sheet.py
fastuiwidgets/common/theme_listener.py
fastuiwidgets/common/translator.py
fastuiwidgets/components/__init__.py
fastuiwidgets/components/date_time/__init__.py
fastuiwidgets/components/date_time/calendar_picker.py
fastuiwidgets/components/date_time/calendar_view.py
fastuiwidgets/components/date_time/date_picker.py
fastuiwidgets/components/date_time/fast_calendar_view.py
fastuiwidgets/components/date_time/picker_base.py
fastuiwidgets/components/date_time/time_picker.py
fastuiwidgets/components/dialog_box/__init__.py
fastuiwidgets/components/dialog_box/color_dialog.py
fastuiwidgets/components/dialog_box/dialog.py
fastuiwidgets/components/dialog_box/folder_list_dialog.py
fastuiwidgets/components/dialog_box/mask_dialog_base.py
fastuiwidgets/components/dialog_box/message_box_base.py
fastuiwidgets/components/dialog_box/message_dialog.py
fastuiwidgets/components/layout/__init__.py
fastuiwidgets/components/layout/expand_layout.py
fastuiwidgets/components/layout/flow_layout.py
fastuiwidgets/components/layout/v_box_layout.py
fastuiwidgets/components/material/__init__.py
fastuiwidgets/components/material/acrylic_combo_box.py
fastuiwidgets/components/material/acrylic_flyout.py
fastuiwidgets/components/material/acrylic_line_edit.py
fastuiwidgets/components/material/acrylic_menu.py
fastuiwidgets/components/material/acrylic_tool_tip.py
fastuiwidgets/components/material/acrylic_widget.py
fastuiwidgets/components/navigation/__init__.py
python_fastui_widgets-1.0.3.dist-info/licenses/LICENSE
python_fastui_widgets-1.0.3.dist-info/METADATA
python_fastui_widgets-1.0.3.dist-info/WHEEL
python_fastui_widgets-1.0.3.dist-info/top_level.txt
python_fastui_widgets-1.0.3.dist-info/RECORD
